LICENSE.txt
README.txt
setup.py
sa_tools/README.txt
sa_tools/__init__.py
sa_tools/latex.py
sa_tools/latex.txt
sa_tools/test.py
sa_tools/tools.py
sa_tools/wildcard.txt
sa_tools.egg-info/PKG-INFO
sa_tools.egg-info/SOURCES.txt
sa_tools.egg-info/dependency_links.txt
sa_tools.egg-info/top_level.txt
sa_tools/dump/__init__.py
sa_tools/dump/maxdb.py
sa_tools/scripts/sa2latex.py
sa_tools/tests/__init__.py
sa_tools/tests/tables.py