Metadata-Version: 1.0
Name: sa-tools
Version: 0.0.1
Summary: SQLAlchemy Tools
Home-page: UNKNOWN
Author: Hermann Himmelbauer
Author-email: dusty@qwer.tk
License: LGPL
Platform: UNKNOWN
